gplaydl/__init__.py
gplaydl/__main__.py
gplaydl/gplaydl.py
gplaydl-1.3.3.dist-info/METADATA
gplaydl-1.3.3.dist-info/WHEEL
gplaydl-1.3.3.dist-info/entry_points.txt
gplaydl-1.3.3.dist-info/top_level.txt
gplaydl-1.3.3.dist-info/RECORD
