Metadata-Version: 2.1
Name: gplaydl
Version: 1.3.3
Summary: Google Play APK downloader command line utility that utilizes gpapi to download APK files of free apps and games.
Home-page: https://github.com/rehmatworks/gplaydl
Author: Rehmat Alam
Author-email: contact@rehmat.works
License: MIT
Platform: UNKNOWN
Requires-Python: >3.2.0
Requires-Dist: gpapidl
Requires-Dist: validators
Requires-Dist: termcolor
